README.md
setup.py
visual_pts/__init__.py
visual_pts/util_kitti.py
visual_pts/visual.py
visual_pts/visual_kitti.py
visual_pts/visual_nuscenes.py
visual_pts/visual_point.py
visual_pts.egg-info/PKG-INFO
visual_pts.egg-info/SOURCES.txt
visual_pts.egg-info/dependency_links.txt
visual_pts.egg-info/requires.txt
visual_pts.egg-info/top_level.txt