Metadata-Version: 1.2
Name: visual-pts
Version: 1.5.0
Summary: Visualize Point Clouds (with bbox) by Plotly
Home-page: https://github.com/gaojunbin/visual_pts
Author: JunbinGao, HaoRuan, LianguangLiu
Author-email: junbingao@hust.edu.cn
Maintainer: JunbinGao, HaoRuan, LianguangLiu
Maintainer-email: junbingao@hust.edu.cn
License: MIT
Platform: all
Classifier: Operating System :: OS Independent
Classifier: Programming Language :: Python :: 3
